README.txt
setup.py
archetypes/__init__.py
archetypes.configure.egg-info/PKG-INFO
archetypes.configure.egg-info/SOURCES.txt
archetypes.configure.egg-info/dependency_links.txt
archetypes.configure.egg-info/entry_points.txt
archetypes.configure.egg-info/namespace_packages.txt
archetypes.configure.egg-info/not-zip-safe
archetypes.configure.egg-info/requires.txt
archetypes.configure.egg-info/top_level.txt
archetypes/configure/__init__.py
archetypes/configure/meta.zcml
archetypes/configure/registry.py
archetypes/configure/zcml.py
archetypes/configure/tests/__init__.py
archetypes/configure/tests/content.py
archetypes/configure/tests/test_zcml.py
docs/HISTORY.txt
docs/LICENSE.GPL
docs/LICENSE.txt