Metadata-Version: 1.0
Name: archetypes.configure
Version: 0.2
Summary: Declarative content type configuration for Archetypes.
Home-page: UNKNOWN
Author: Plone Foundation
Author-email: plone-developers@lists.sourceforge.net
License: GPL
Platform: UNKNOWN
Classifier: Framework :: Plone
Classifier: Intended Audience :: Developers
Classifier: License :: OSI Approved :: GNU General Public License (GPL)
